pypi_download_pkg/__init__.py
pypi_download_pkg/cli.py
pypi_download_pkg-0.2.5.dist-info/METADATA
pypi_download_pkg-0.2.5.dist-info/WHEEL
pypi_download_pkg-0.2.5.dist-info/entry_points.txt
pypi_download_pkg-0.2.5.dist-info/licenses/LICENSE
pypi_download_pkg-0.2.5.dist-info/RECORD
