Metadata-Version: 2.4
Name: pypi-download-pkg
Version: 0.2.5
License-File: LICENSE
Requires-Python: ~=3.10
Requires-Dist: requests<3,>=2.31.0
